{
  "word": "benign",
  "wordRoot": [
    {
      "title": "<span id=\"#11043\" class=\"scroll-m-16 text-3xl font-bold flex items-center\"><h1 class=\"inline !mb-1 scroll-m-16 text-3xl font-bold\">benign</h1><div class=\"pl-2 flex-1 text-textSecondary text-xl font-serif\">(adj.)</div></span>",
      "html": "<p>\"性情温和的； 亲切的； 仁慈的； 有利的\"，早在14世纪就出现了，源自古法语 <span class=\"foreign notranslate\">benigne</span> \"kind, benign, merciful, gracious\"（12世纪，现代法语 <span class=\"foreign notranslate\">bénin</span>，女性形式 <span class=\"foreign notranslate\">bénigne</span>），源自拉丁语 <span class=\"foreign notranslate\">benignus</span> \"kindly, kindhearted, friendly, generous\"，字面意思是\"出身良好\"，来自 <span class=\"foreign notranslate\">bene</span> \"well\"（参见 <a href=\"/cn/word/bene-\" title=\"Etymology, meaning and definition of bene- \" class=\"crossreference notranslate\">bene-</a>)和 <span class=\"foreign notranslate\">gignere</span> \"to bear, beget\"，来自 <span class=\"foreign notranslate\">genus</span> \"birth\"（源自 PIE 词根 <a href=\"/cn/word/*gene-\" title=\"Etymology, meaning and definition of *gene- \" rel=\"nofollow\" class=\"crossreference notranslate\">*gene-</a> \"give birth, beget\"）。与 <a href=\"/cn/word/gentle\" title=\"Etymology, meaning and definition of gentle \" class=\"crossreference notranslate\">gentle</a> 、<a href=\"/cn/word/kind\" title=\"Etymology, meaning and definition of kind \" class=\"crossreference notranslate\">kind</a>（形容词）、<a href=\"/cn/word/generous\" title=\"Etymology, meaning and definition of generous \" class=\"crossreference notranslate\">generous</a> 等词的意义演变类似。相关词汇： <span class=\"foreign notranslate\">Benignly</span>。</p><ins class=\"adsbygoogle relative inline-block transition-all inline-block h-[250px] w-[300px]\" data-ad-slot=\"4000736339\" data-adtest=\"off\" data-ad-format=\"auto\" data-full-width-responsive=\"true\"></ins>"
    }
  ],
  "relate": [
    {
      "title": "generous<div class=\"pl-2 flex-1 text-textSecondary text-xl font-serif\">(adj.)</div>",
      "html": "<p>\"贵族的\"，来自于法语 <i class=\"foreign notranslate\">généreux</i>（14世纪），源自拉丁语 <i class=\"foreign notranslate\">generosus</i>，意为\"贵族的\"，比喻为\"宽宏大量的，慷慨的\"，源自 <i class=\"foreign notranslate\">genus</i>（属格 <i class=\"foreign notranslate\">generis</i>）\"种族，家族\"（源自 PIE 词根 <a rel=\"nofollow\" title=\"Etymology, meaning and definition of *gene- \" class=\"crossreference notranslate\" href=\"/cn/word/*gene-\">*gene-</a>，意为\"生育，产生\"，派生词指代生育、家庭和部落群体）。英语中\"无私的\"（1690年代）和\"丰富的\"（1610年代）的次要意义在法语和拉丁语中也存在。相关词汇： <i class=\"foreign notranslate\">Generously</i>； <i class=\"foreign notranslate\">generousness</i>。</p>"
    },
    {
      "title": "gentle<div class=\"pl-2 flex-1 text-textSecondary text-xl font-serif\">(adj.)</div>",
      "html": "<p>词源来自13世纪早期，<i class=\"foreign notranslate\">gentile</i>、<i class=\"foreign notranslate\">gentle</i>意为“出生高贵，有贵族血统或家族背景”，源于古法语<i class=\"foreign notranslate\">gentil</i>/<i class=\"foreign notranslate\">jentil</i>“高贵出生，有价值的，勇敢的，英勇的；精致的，良好的，公正的”（11世纪，现代法语中是“宜人的，优雅的，令人愉悦的；精美的，俏丽的”）以及直接来自拉丁语<i class=\"foreign notranslate\">gentilis</i>“同族或宗族的”，中世纪拉丁语中指“有高贵或良好出生”，来自<i class=\"foreign notranslate\">gens</i>（属格<i class=\"foreign notranslate\">gentis</i>）“种族，氏族”，来自词根<i class=\"foreign notranslate\">gignere</i>“生育”，来自PIE词根<i class=\"foreign notranslate\">*gene-</i>“生育，繁衍”，这个PIE词根<a rel=\"nofollow\" title=\"Etymology, meaning and definition of *gene- \" class=\"crossreference notranslate\" href=\"/cn/word/*gene-\">*gene-</a>也是“繁衍生息”的意思，附属词用于指代生殖以及家族和部落团体。</p><p>在英语和法语中，“gentle”的含义演变为“具有高贵出生或贵族身份的品格或举止”，这种品格或举止的定义根据不同时代有所不同。从13世纪中期在英语中意为“亲切的、友好的”（现在已不再使用），为基督徒或骑士贵族所礼遇的举止。从13世纪末意为“有礼貌的、彬彬有礼的、有教养的、迷人的”；大约1300年时指“优雅的、美丽的”。意为“温柔的、温和的；容易的；不刺激的”（用于动物、事物、人）是从16世纪50年代开始的。较早的含义保留在<a title=\"Etymology, meaning and definition of gentleman \" class=\"crossreference notranslate\" href=\"/cn/word/gentleman\">gentleman</a>中，同时比较<a title=\"Etymology, meaning and definition of gentile \" class=\"crossreference notranslate\" href=\"/cn/word/gentile\">gentile</a>（形容词），一个保留了拉丁语圣经含义的变体形式（尽管在中古英语中<i class=\"foreign notranslate\">gentle</i>有时意指“异教徒、非信徒”），还有<a title=\"Etymology, meaning and definition of genteel \" class=\"crossreference notranslate\" href=\"/cn/word/genteel\">genteel</a>，这是从法语中再次借用的同一单词。从1823年起还有“与仙子有关”的意思。</p>"
    }
  ]
}