{
  "word": "blouse",
  "wordRoot": [
    {
      "title": "<span id=\"#13629\" class=\"scroll-m-16 text-3xl font-bold flex items-center\"><h1 class=\"inline !mb-1 scroll-m-16 text-3xl font-bold\">blouse</h1><div class=\"pl-2 flex-1 text-textSecondary text-xl font-serif\">(n.)</div></span>",
      "html": "<p>\"轻便的亚麻或棉质上衣\"，1828年（从1822年开始作为法语词汇进入英语），源自法语 <span class=\"foreign notranslate\">blouse</span>，\"工人或农民的罩衫\"（1788年），其起源不明。也许它与普罗旺斯语 <span class=\"foreign notranslate\">(lano) blouso</span> \"短（羊毛）\" [Gamillscheg] 有关。另一个建议[Klein]是它来自中世纪拉丁语 <span class=\"foreign notranslate\">pelusia</span>，来自上埃及的 <span class=\"foreign notranslate\">Pelusium</span>，据说是中世纪的服装制造中心。</p><ins class=\"adsbygoogle relative inline-block transition-all inline-block h-[250px] w-[300px]\" data-ad-slot=\"4000736339\" data-adtest=\"off\" data-ad-format=\"auto\" data-full-width-responsive=\"true\"></ins><p>起初是法国工人穿的一种衣服，用于防尘等，后来被女性和儿童时尚地采用，但也有反对声音：</p><blockquote class=\"bq-origin\">In Paris, a very slovenly, loose, drawn frock, with most capacious sleeves, had been introduced called a <i class=\"foreign notranslate\">blouse</i>. Some of our priestesses of the toilet seemed emulous of copying this deshabille, with some slight alterations, but we never wish to see it on the symmetrical form of a British lady. [\"Summary of Fashion for 1822,\" in Museum of Foreign Literature and Science, Jan.-June 1823]</blockquote><blockquote>在巴黎，一种非常邋遢、宽松、有很大袖子的连衣裙被引入，叫做 <i class=\"foreign notranslate\">blouse</i>。我们的一些时尚女祭司似乎很想模仿这种不整洁的穿着，稍加改动，但我们从不希望看到它出现在英国女士的匀称身材上。[\"外国文学和科学博物馆1823年1-6月时尚总结\"]</blockquote>"
    }
  ],
  "relate": []
}