{
  "word": "cell",
  "wordRoot": [
    {
      "title": "<span id=\"#8331\" class=\"scroll-m-16 text-3xl font-bold flex items-center\"><h1 class=\"inline !mb-1 scroll-m-16 text-3xl font-bold\">cell</h1><div class=\"pl-2 flex-1 text-textSecondary text-xl font-serif\">(n.)</div></span>",
      "html": "<p>早期的12世纪，\"小修道院，隶属修道院\"（从拉丁语在这个意义上的中世纪拉丁语中而来），之后变为 \"修道院中僧侣或修女的小房间； 隐士的住所\" （约1300年），源自拉丁语  <span class=\"foreign notranslate\">cella</span>  \"小房间，贮藏室，小屋\"，与拉丁语  <span class=\"foreign notranslate\">celare</span>  \"隐藏，隐瞒\"相关（来自 PIE 词根  <a href=\"/cn/word/*kel-\" title=\"Etymology, meaning and definition of *kel-  \" rel=\"nofollow\" class=\"crossreference notranslate\">*kel- </a>  （1）\"盖住，隐瞒，保存\"）。</p><ins class=\"adsbygoogle relative inline-block transition-all inline-block h-[250px] w-[300px]\" data-ad-slot=\"4000736339\" data-adtest=\"off\" data-ad-format=\"auto\" data-full-width-responsive=\"true\"></ins><p>从\"修道院房间\"的意义扩展为 \"监狱房间\"（1722年）。14世纪的时候，这个词在比喻上被用于大脑的 \"隔间\" 作为某种能力的所在地。到了17世纪，它被用于各种空腔（木材结构，水果片段，蜜蜂蜂巢），逐渐聚焦到现代 \"所有生命体的基本结构\" 的意义上（OED 将其追溯到1845年）。</p><p>电池的意义来自1828年，基于早期类型的 \"隔间\"。 \"在较大组织中工作的小团体\" 的含义来自1925年。 <strong><i class=\"foreign notranslate\">Cell-body</i></strong> 来自1851年，<strong><i class=\"foreign notranslate\">cell-division</i></strong> 来自1846年，<strong><i class=\"foreign notranslate\">cell-membrane</i></strong> 来自1837年（<strong><i class=\"foreign notranslate\">cellular membrane</i></strong>在1732年就已被证实），<strong><i class=\"foreign notranslate\">cell wall</i></strong> 的使用可以追溯到1842年。</p>"
    }
  ],
  "relate": [
    {
      "title": "Brussels<div class=\"pl-2 flex-1 text-textSecondary text-xl font-serif\"></div>",
      "html": "<p>“布拉班特”，古布拉班特地区和现代比利时的首都，名称源自日耳曼语，由“ <i class=\"foreign notranslate\">brocca</i> ”（沼泽）和“ <i class=\"foreign notranslate\">sali</i> ”（房间，建筑）组成，源自拉丁语的“ <i class=\"foreign notranslate\">cella</i> ”（见 <a title=\"Etymology, meaning and definition of cell \" class=\"crossreference notranslate\" href=\"/cn/word/cell\">cell</a> ）。在河流上的一个岛上建立了6世纪的要塞。1799年作为地毯的一种类型被引用； 1748年作为一种花边的类型被引用。</p><p><i class=\"foreign notranslate\"><strong>Brussels sprouts</strong></i> （ <i class=\"foreign notranslate\">Brassica oleracea gemmifera</i> ）可追溯到1748年（其第一份书面描述来自1580年代）； 它们长期以来一直与佛兰德斯地区和尤其是布鲁塞尔相联系（与法语名称 <i class=\"foreign notranslate\">choux de Bruxelles</i> 相比较）。</p>"
    },
    {
      "title": "celled<div class=\"pl-2 flex-1 text-textSecondary text-xl font-serif\">(adj.)</div>",
      "html": "<p>在化合物中，“具有细胞”（特定数量或类型的细胞），始于18世纪末，源自 <a title=\"Etymology, meaning and definition of cell \" class=\"crossreference notranslate\" href=\"/cn/word/cell\">cell</a>（名词）。</p>"
    }
  ]
}