{
  "word": "deaf",
  "wordRoot": [
    {
      "title": "<span id=\"#812\" class=\"scroll-m-16 text-3xl font-bold flex items-center\"><h1 class=\"inline !mb-1 scroll-m-16 text-3xl font-bold\">deaf</h1><div class=\"pl-2 flex-1 text-textSecondary text-xl font-serif\">(adj.)</div></span>",
      "html": "<p>“Old English <span class=\"foreign notranslate\">deaf</span>（聋的）也指“空的，贫瘠的”，源自原始日耳曼语 <span class=\"foreign notranslate\">*daubaz</span>（也指古撒克逊语 <span class=\"foreign notranslate\">dof</span>，古诺尔斯语 <span class=\"foreign notranslate\">daufr</span>，古弗里斯兰语 <span class=\"foreign notranslate\">daf</span>，荷兰语 <span class=\"foreign notranslate\">doof</span>，德语 <span class=\"foreign notranslate\">taub</span>，哥特语 <span class=\"foreign notranslate\">daufs</span>），源自原始印欧语 <span class=\"foreign notranslate\">dheubh-</span>, 用于构成表示“混乱，昏迷，头晕”的词汇（源自希腊语 <span class=\"foreign notranslate\">typhlos</span> “盲”， <span class=\"foreign notranslate\">typhein</span> “冒烟”； 古英语 <span class=\"foreign notranslate\">dumb</span> “不能说话”； 古高地德语 <span class=\"foreign notranslate\">tumb</span>）。</p><ins class=\"adsbygoogle relative inline-block transition-all inline-block h-[250px] w-[300px]\" data-ad-slot=\"4000736339\" data-adtest=\"off\" data-ad-format=\"auto\" data-full-width-responsive=\"true\"></ins><p>这个词在18世纪之前的发音与 <i class=\"foreign notranslate\">reef</i>（礁）押韵。指“拒绝听或听不见”的意思始于公元1200年。作为名词，“聋人”始于公元1200年。 <i class=\"foreign notranslate\"><strong>Deaf-mute</strong></i>（聋哑人）源自1837年的法语 <i class=\"foreign notranslate\">sourd-muet</i>。在18世纪至19世纪的英国，聋哑人被当作算命者。古英语 <i class=\"foreign notranslate\"><strong>Deaf as an adder</strong></i>（像毒蛇一样聋）源自诗篇 lviii.5（见 <a title=\"Etymology, meaning and definition of adder \" class=\"crossreference notranslate\" href=\"/cn/word/adder\">adder</a>）。</p>"
    }
  ],
  "relate": [
    {
      "title": "adder<div class=\"pl-2 flex-1 text-textSecondary text-xl font-serif\">(n.)</div>",
      "html": "<blockquote><p>中古英语 <i class=\"foreign notranslate\">naddre</i> 来自古英语（西萨克森语）<i class=\"foreign notranslate\">næddre</i>（中部英语 <i class=\"foreign notranslate\">nedre</i>，诺森伯兰语 <i class=\"foreign notranslate\">nedra</i>），“一条蛇； 伊甸园里的蛇”，来自原始日耳曼语 <i class=\"foreign notranslate\">*naethro</i> “一条蛇”（来源于古诺尔斯语 <i class=\"foreign notranslate\">naðra</i>，中荷兰语 <i class=\"foreign notranslate\">nadre</i>，古高地德语 <i class=\"foreign notranslate\">natra</i>，德语 <i class=\"foreign notranslate\">Natter</i>，哥特语 <i class=\"foreign notranslate\">nadrs</i>），源于词根 <i class=\"foreign notranslate\">*nētr-</i> “蛇”（拉丁语 <i class=\"foreign notranslate\">natrix</i> “水蛇”（这个词的意思可能是通过与 <i class=\"foreign notranslate\">nare</i> “游泳”的民间联想而来）； 古爱尔兰语 <i class=\"foreign notranslate\">nathir</i>，威尔士语 <i class=\"foreign notranslate\">neidr</i> “蛇，毒蛇”）。</p><p>现代形式代表了14世纪至16世纪 <i class=\"foreign notranslate\">a nadder</i> 错误划分为 <i class=\"foreign notranslate\">an adder</i> 的结果。参见 <a title=\"Etymology, meaning and definition of apron \" class=\"crossreference notranslate\" href=\"/cn/word/apron\">apron</a> 、<a title=\"Etymology, meaning and definition of auger \" class=\"crossreference notranslate\" href=\"/cn/word/auger\">auger</a> 、<a title=\"Etymology, meaning and definition of nickname \" class=\"crossreference notranslate\" href=\"/cn/word/nickname\">nickname</a> 、<a title=\"Etymology, meaning and definition of orange \" class=\"crossreference notranslate\" href=\"/cn/word/orange\">orange</a> 、<a title=\"Etymology, meaning and definition of humble pie \" class=\"crossreference notranslate\" href=\"/cn/word/humble%20pie\">humble pie</a> 、<a title=\"Etymology, meaning and definition of aitchbone \" class=\"crossreference notranslate\" href=\"/cn/word/aitchbone\">aitchbone</a> 、<a title=\"Etymology, meaning and definition of umpire \" class=\"crossreference notranslate\" href=\"/cn/word/umpire\">umpire</a>。 <i class=\"foreign notranslate\">Nedder</i> 仍然是英格兰北部的方言形式。</p><p>自中古英语以来，这个词的使用被限制为指蝰蛇的通用名称，是英国唯一有毒的爬行动物（虽然通常对人类不致命），后来也推广到了其他地方的有毒蛇或类似蛇（<i class=\"foreign notranslate\">puff-adder</i> 等）。与聋的民间传说联系起来是通过诗篇 LVIII.1-5。<br>据说，蝰蛇堵上耳朵，以避免听到被召唤来驱赶它的耍蛇人的声音。</p></blockquote>"
    },
    {
      "title": "deafen<div class=\"pl-2 flex-1 text-textSecondary text-xl font-serif\">(v.)</div>",
      "html": "<p>1590年代，“使聋”，来自 <a title=\"Etymology, meaning and definition of deaf \" class=\"crossreference notranslate\" href=\"/cn/word/deaf\">deaf</a> + <a title=\"Etymology, meaning and definition of -en \" class=\"crossreference notranslate\" href=\"/cn/word/-en\">-en</a>（1）。更早的动词是简单的 <i class=\"foreign notranslate\">deaf</i>（15世纪中期）。对于“变聋，变聋”，古英语有 <i class=\"foreign notranslate\">adeafian</i>（不及物动词），它在中古英语中幸存为 <i class=\"foreign notranslate\">deave</i>，但从14世纪中叶开始具有及物意义，并从使用中消失，除了方言（在方言中它主要具有及物和比喻意义），使英语在这里没有不及物动词。相关： <i class=\"foreign notranslate\">Deafened</i>。</p>"
    },
    {
      "title": "deafness<div class=\"pl-2 flex-1 text-textSecondary text-xl font-serif\">(n.)</div>",
      "html": "<p>\"无法区分或感知声音\"，14世纪晚期， <i class=\"foreign notranslate\">defnesse</i>，来自 <a title=\"Etymology, meaning and definition of deaf \" class=\"crossreference notranslate\" href=\"/cn/word/deaf\">deaf</a> + <a title=\"Etymology, meaning and definition of -ness \" class=\"crossreference notranslate\" href=\"/cn/word/-ness\">-ness</a>。</p>"
    }
  ]
}