{
  "word": "display",
  "wordRoot": [
    {
      "title": "<span id=\"#11475\" class=\"scroll-m-16 text-3xl font-bold flex items-center\"><h1 class=\"inline !mb-1 scroll-m-16 text-3xl font-bold\">display</h1><div class=\"pl-2 flex-1 text-textSecondary text-xl font-serif\">(v.)</div></span>",
      "html": "<p>约于1300年，“展开，铺开，展示”（旗帜等），源自古法语 <span class=\"foreign notranslate\">desploiir</span>（现代法语 <span class=\"foreign notranslate\">déployer</span>）“展开，解开，铺开”（用于解开结、密封信件等），源自拉丁语 <span class=\"foreign notranslate\">displicare</span> “散开”，在中世纪拉丁语中意为“展开”，由 <span class=\"foreign notranslate\">dis-</span> “不，分开”（见 <a href=\"/cn/word/dis-\" title=\"Etymology, meaning and definition of dis- \" class=\"crossreference notranslate\">dis-</a>)和 <span class=\"foreign notranslate\">plicare</span> “折叠”（源自 PIE 词根 <a href=\"/cn/word/*plek-\" title=\"Etymology, meaning and definition of *plek- \" rel=\"nofollow\" class=\"crossreference notranslate\">*plek-</a> “编织”）组成。</p><ins class=\"adsbygoogle relative inline-block transition-all inline-block h-[250px] w-[300px]\" data-ad-slot=\"4000736339\" data-adtest=\"off\" data-ad-format=\"auto\" data-full-width-responsive=\"true\"></ins><p>正确地用于帆或旗帜（与 <i class=\"foreign notranslate\">play</i> 无关）； “揭示，展示，暴露于视野中”的意义出现在14世纪晚期； “无意中揭示，被看到”的意义始于约1600年。相关词汇： <i class=\"foreign notranslate\">Displayed</i>； <i class=\"foreign notranslate\">displaying</i>。</p>"
    },
    {
      "title": "<h2 id=\"#46780\" class=\"scroll-m-16 text-3xl font-bold flex items-center\">display<div class=\"pl-2 flex-1 text-textSecondary text-xl font-serif\">(n.)</div></h2>",
      "html": "<p>1580年代，“描述”的意义现已过时，源自 <a title=\"Etymology, meaning and definition of display \" class=\"crossreference notranslate\" href=\"/cn/word/display\">display</a>（动词）。“展览，将任何事物展示给视野”，通常带有炫耀或追求效果的暗示，始于1680年代。指“在屏幕上呈现电子信号”的意义最早出现在1945年，指雷达，到1960年代指计算机。 <i class=\"foreign notranslate\">Display-window</i> 最早见于1893年。</p><a title=\"Etymology, meaning and definition of display \" class=\"crossreference notranslate\" href=\"/cn/word/display\">display</a> 的翻译优先为“展示”或“显示”， <i class=\"foreign notranslate\">Display-window</i> 的翻译为“显示窗口”。文章流畅度已经改善。"
    }
  ],
  "relate": [
    {
      "title": "splay<div class=\"pl-2 flex-1 text-textSecondary text-xl font-serif\">(v.)</div>",
      "html": "<p> 14世纪早期，“展开，舒展”（现在已不再使用），约在1400年，“展开”，是 <i class=\"foreign notranslate\">desplayen</i> 的缩写形式（参见 <a title=\"Etymology, meaning and definition of display \" class=\"crossreference notranslate\" href=\"/cn/word/display\">display</a>（v.））。</p><p> 1848年有“笨拙地散开”的意思; 过去分词形容词 <i class=\"foreign notranslate\">splayed</i> 自1540年代开始出现，表示“扩展，展开”。 1540年代出现了 <i class=\"foreign notranslate\">Splay-foot</i>，指宽大、向外翻转的脚。 作为建筑学名词的 <i class=\"foreign notranslate\">Splay</i> 可追溯至大约1500年。</p>"
    },
    {
      "title": "dis-<div class=\"pl-2 flex-1 text-textSecondary text-xl font-serif\"></div>",
      "html": "<p>拉丁语词缀，意为1. “缺乏，不”（如 <a title=\"Etymology, meaning and definition of dishonest \" class=\"crossreference notranslate\" href=\"/cn/word/dishonest\">dishonest</a>）； 2. “相反，做相反的事”（如 <a title=\"Etymology, meaning and definition of disallow \" class=\"crossreference notranslate\" href=\"/cn/word/disallow\">disallow</a>）； 3. “分开，离开”（如 <a title=\"Etymology, meaning and definition of discard \" class=\"crossreference notranslate\" href=\"/cn/word/discard\">discard</a>），源自古法语 <i class=\"foreign notranslate\">des-</i> 或直接源自拉丁语 <i class=\"foreign notranslate\">dis-</i>，意为“分开，分离，朝不同方向，比喻为‘不，非’，也表示‘极其，完全’。在大多数有声辅音前，它被同化为 <i class=\"foreign notranslate\">dif-</i>，在 <i class=\"foreign notranslate\">-f-</i> 前被同化为 <i class=\"foreign notranslate\">di-</i>。</p><p>拉丁语前缀来自原始印欧语言的 <i class=\"foreign notranslate\">*dis-</i>，意为“分开，分离”（源自古英语 <i class=\"foreign notranslate\">te-</i>，古撒克逊语 <i class=\"foreign notranslate\">ti-</i>，古高地德语 <i class=\"foreign notranslate\">ze-</i>，德语 <i class=\"foreign notranslate\">zer-</i>）。原始印欧语言的根词是 <i class=\"foreign notranslate\">*dwis-</i> 的次生形式，因此与拉丁语 <i class=\"foreign notranslate\">bis</i> “两次”（最初为 <i class=\"foreign notranslate\">*dvis</i>）和 <i class=\"foreign notranslate\">duo</i> 有关，表示“两种方式，分开”（因此表示“分开，分离”）。</p><p>在古典拉丁语中， <i class=\"foreign notranslate\">dis-</i> 与 <a title=\"Etymology, meaning and definition of de- \" class=\"crossreference notranslate\" href=\"/cn/word/de-\">de-</a> 相似，意思也差不多，但在后期拉丁语中， <i class=\"foreign notranslate\">dis-</i> 成为首选形式，并传入古法语中，成为古法语中形成复合词的形式，越来越具有否定意义（“不”）。在英语中，许多这些词最终被改回了 <i class=\"foreign notranslate\">dis-</i>，而在法语中，许多词被改回了 <i class=\"foreign notranslate\">de-</i>。通常存在混淆。</p><p>作为英语中的一个活前缀，它反转或否定了它所附着的词。有时，如意大利语中，它被缩减为 <i class=\"foreign notranslate\">s-</i>（如 <a title=\"Etymology, meaning and definition of spend \" class=\"crossreference notranslate\" href=\"/cn/word/spend\">spend</a>， <a title=\"Etymology, meaning and definition of splay \" class=\"crossreference notranslate\" href=\"/cn/word/splay\">splay</a>， <a title=\"Etymology, meaning and definition of sport \" class=\"crossreference notranslate\" href=\"/cn/word/sport\">sport</a>， <i class=\"foreign notranslate\">sdain</i> 表示 <a title=\"Etymology, meaning and definition of disdain \" class=\"crossreference notranslate\" href=\"/cn/word/disdain\">disdain</a>，以及姓氏 <a title=\"Etymology, meaning and definition of Spencer \" class=\"crossreference notranslate\" href=\"/cn/word/Spencer\">Spencer</a> 和 <i class=\"foreign notranslate\">Spence</i>）。</p>"
    },
    {
      "title": "*plek-<div class=\"pl-2 flex-1 text-textSecondary text-xl font-serif\"></div>",
      "html": "<p>原始印欧语根词，意为“编织”。它是根词 <a rel=\"nofollow\" title=\"Etymology, meaning and definition of *pel- \" class=\"crossreference notranslate\" href=\"/cn/word/*pel-\">*pel-</a>（2）“折叠”的扩展形式。</p><p>它构成或部分构成以下单词： <a title=\"Etymology, meaning and definition of accomplice \" class=\"crossreference notranslate\" href=\"/cn/word/accomplice\">accomplice</a>; <a title=\"Etymology, meaning and definition of application \" class=\"crossreference notranslate\" href=\"/cn/word/application\">application</a>; <a title=\"Etymology, meaning and definition of apply \" class=\"crossreference notranslate\" href=\"/cn/word/apply\">apply</a>; <a title=\"Etymology, meaning and definition of complex \" class=\"crossreference notranslate\" href=\"/cn/word/complex\">complex</a>; <a title=\"Etymology, meaning and definition of complexion \" class=\"crossreference notranslate\" href=\"/cn/word/complexion\">complexion</a>; <a title=\"Etymology, meaning and definition of complicate \" class=\"crossreference notranslate\" href=\"/cn/word/complicate\">complicate</a>; <a title=\"Etymology, meaning and definition of complication \" class=\"crossreference notranslate\" href=\"/cn/word/complication\">complication</a>; <a title=\"Etymology, meaning and definition of complicity \" class=\"crossreference notranslate\" href=\"/cn/word/complicity\">complicity</a>; <a title=\"Etymology, meaning and definition of deploy \" class=\"crossreference notranslate\" href=\"/cn/word/deploy\">deploy</a>; <a title=\"Etymology, meaning and definition of display \" class=\"crossreference notranslate\" href=\"/cn/word/display\">display</a>; <a title=\"Etymology, meaning and definition of duplex \" class=\"crossreference notranslate\" href=\"/cn/word/duplex\">duplex</a>; <a title=\"Etymology, meaning and definition of duplicate \" class=\"crossreference notranslate\" href=\"/cn/word/duplicate\">duplicate</a>; <a title=\"Etymology, meaning and definition of duplicity \" class=\"crossreference notranslate\" href=\"/cn/word/duplicity\">duplicity</a>; <a title=\"Etymology, meaning and definition of employ \" class=\"crossreference notranslate\" href=\"/cn/word/employ\">employ</a>; <a title=\"Etymology, meaning and definition of explicate \" class=\"crossreference notranslate\" href=\"/cn/word/explicate\">explicate</a>; <a title=\"Etymology, meaning and definition of explicit \" class=\"crossreference notranslate\" href=\"/cn/word/explicit\">explicit</a>; <a title=\"Etymology, meaning and definition of exploit \" class=\"crossreference notranslate\" href=\"/cn/word/exploit\">exploit</a>; <a title=\"Etymology, meaning and definition of flax \" class=\"crossreference notranslate\" href=\"/cn/word/flax\">flax</a>; <a title=\"Etymology, meaning and definition of implex \" class=\"crossreference notranslate\" href=\"/cn/word/implex\">implex</a>; <a title=\"Etymology, meaning and definition of implicate \" class=\"crossreference notranslate\" href=\"/cn/word/implicate\">implicate</a>; <a title=\"Etymology, meaning and definition of implication \" class=\"crossreference notranslate\" href=\"/cn/word/implication\">implication</a>; <a title=\"Etymology, meaning and definition of implicit \" class=\"crossreference notranslate\" href=\"/cn/word/implicit\">implicit</a>; <a title=\"Etymology, meaning and definition of imply \" class=\"crossreference notranslate\" href=\"/cn/word/imply\">imply</a>; <a title=\"Etymology, meaning and definition of multiply \" class=\"crossreference notranslate\" href=\"/cn/word/multiply\">multiply</a>; <a title=\"Etymology, meaning and definition of perplex \" class=\"crossreference notranslate\" href=\"/cn/word/perplex\">perplex</a>; <a title=\"Etymology, meaning and definition of perplexity \" class=\"crossreference notranslate\" href=\"/cn/word/perplexity\">perplexity</a>; <a title=\"Etymology, meaning and definition of plait \" class=\"crossreference notranslate\" href=\"/cn/word/plait\">plait</a>; <a title=\"Etymology, meaning and definition of plash \" class=\"crossreference notranslate\" href=\"/cn/word/plash#etymonline_v_46503\">plash</a> (v.2) “交织”； <a title=\"Etymology, meaning and definition of pleat \" class=\"crossreference notranslate\" href=\"/cn/word/pleat\">pleat</a>; <a title=\"Etymology, meaning and definition of -plex \" class=\"crossreference notranslate\" href=\"/cn/word/-plex\">-plex</a>; <a title=\"Etymology, meaning and definition of plexus \" class=\"crossreference notranslate\" href=\"/cn/word/plexus\">plexus</a>; <a title=\"Etymology, meaning and definition of pliable \" class=\"crossreference notranslate\" href=\"/cn/word/pliable\">pliable</a>; <a title=\"Etymology, meaning and definition of pliant \" class=\"crossreference notranslate\" href=\"/cn/word/pliant\">pliant</a>; <a title=\"Etymology, meaning and definition of plie \" class=\"crossreference notranslate\" href=\"/cn/word/plie\">plie</a>; <a title=\"Etymology, meaning and definition of plight \" class=\"crossreference notranslate\" href=\"/cn/word/plight#etymonline_v_16502\">plight</a> (n.1) “状况或状态”； <a title=\"Etymology, meaning and definition of ply \" class=\"crossreference notranslate\" href=\"/cn/word/ply#etymonline_v_17510\">ply</a> (v.1) “使用； 从事”； <a title=\"Etymology, meaning and definition of ply \" class=\"crossreference notranslate\" href=\"/cn/word/ply#etymonline_v_46582\">ply</a> (v.2) “弯曲”； <a title=\"Etymology, meaning and definition of ply \" class=\"crossreference notranslate\" href=\"/cn/word/ply#etymonline_v_17511\">ply</a> (n.) “一层，褶皱”； <a title=\"Etymology, meaning and definition of replica \" class=\"crossreference notranslate\" href=\"/cn/word/replica\">replica</a>; <a title=\"Etymology, meaning and definition of replicate \" class=\"crossreference notranslate\" href=\"/cn/word/replicate\">replicate</a>; <a title=\"Etymology, meaning and definition of replication \" class=\"crossreference notranslate\" href=\"/cn/word/replication\">replication</a>; <a title=\"Etymology, meaning and definition of reply \" class=\"crossreference notranslate\" href=\"/cn/word/reply\">reply</a>; <a title=\"Etymology, meaning and definition of simplex \" class=\"crossreference notranslate\" href=\"/cn/word/simplex\">simplex</a>; <a title=\"Etymology, meaning and definition of splay \" class=\"crossreference notranslate\" href=\"/cn/word/splay\">splay</a>; <a title=\"Etymology, meaning and definition of triplicate \" class=\"crossreference notranslate\" href=\"/cn/word/triplicate\">triplicate</a>。</p><p>它是以下单词的假设来源/其存在的证据由以下单词提供：梵语 <i class=\"foreign notranslate\">prasna-</i> “头巾”； 希腊语 <i class=\"foreign notranslate\">plekein</i> “编织，编辫子，缠绕，盘绕”， <i class=\"foreign notranslate\">plektos</i> “扭曲的”； 拉丁语 <i class=\"foreign notranslate\">plicare</i> “放置，折叠，扭曲”， <i class=\"foreign notranslate\">plectere</i>（过去分词 <i class=\"foreign notranslate\">plexus</i>）“编织，编辫子，交织”； 古教会斯拉夫语 <i class=\"foreign notranslate\">plesti</i> “编织，编辫子，扭曲”，俄语 <i class=\"foreign notranslate\">plesti</i>； 哥特语 <i class=\"foreign notranslate\">flahta</i> “辫子”； 古诺尔斯语 <i class=\"foreign notranslate\">fletta</i>，古高地德语 <i class=\"foreign notranslate\">flehtan</i> “编织”； 古英语 <i class=\"foreign notranslate\">fleax</i> “用亚麻制成的布料，亚麻布”。</p>"
    }
  ]
}