{
  "word": "economy",
  "wordRoot": [
    {
      "title": "<span id=\"#980\" class=\"scroll-m-16 text-3xl font-bold flex items-center\"><h1 class=\"inline !mb-1 scroll-m-16 text-3xl font-bold\">economy</h1><div class=\"pl-2 flex-1 text-textSecondary text-xl font-serif\">(n.)</div></span>",
      "html": "<p>1530年代，\"家庭管理\"，源自拉丁语 <span class=\"foreign notranslate\">oeconomia</span>（法语 <span class=\"foreign notranslate\">économie</span>，西班牙语 <span class=\"foreign notranslate\">economia</span>，德语 <span class=\"foreign notranslate\">Ökonomie</span> 等的来源），源自希腊语 <span class=\"foreign notranslate\">oikonomia</span> \"家庭管理，节俭\"，源自 <span class=\"foreign notranslate\">oikonomos</span> \"经理，管家\"，源自 <span class=\"foreign notranslate\">oikos</span> \"房屋，住所\"（与拉丁语 <span class=\"foreign notranslate\">vicus</span> \"地区\"， <span class=\"foreign notranslate\">vicinus</span> \"附近\"； 古英语 <span class=\"foreign notranslate\">wic</span> \"住宅，村庄\"同源，源自 PIE 词根 <a href=\"/cn/word/*weik-\" title=\"Etymology, meaning and definition of *weik-  \" rel=\"nofollow\" class=\"crossreference notranslate\">*weik- </a> (1)  \"氏族\"）+ <span class=\"foreign notranslate\">nomos</span> \"管理\"，源自 <span class=\"foreign notranslate\">nemein</span> \"管理\"（源自 PIE 词根 <a href=\"/cn/word/*nem-\" title=\"Etymology, meaning and definition of *nem- \" rel=\"nofollow\" class=\"crossreference notranslate\">*nem-</a> \"分配，分配； 接受\"）。</p><ins class=\"adsbygoogle relative inline-block transition-all inline-block h-[250px] w-[300px]\" data-ad-slot=\"4000736339\" data-adtest=\"off\" data-ad-format=\"auto\" data-full-width-responsive=\"true\"></ins><p>1660年代出现了\"节俭，明智地使用资源\"的意义。\"一个国家的财富和资源\"的意义（缩写为 <i class=\"foreign notranslate\">political economy</i>）可追溯到1650年代，但即使在1780年代，美国的创始人在建立新的共和国时通常只使用 <i class=\"foreign notranslate\">economy</i> 来表示\"节俭\"。在《联邦党人文集》中也是如此，除了一个地方使用了完整的 <i class=\"foreign notranslate\">political economy</i>。</p><blockquote class=\"bq-origin\">Col Mason — He had moved without success for a power to make sumptuary regulations. He had not yet lost sight of his object. After descanting on the extravagance of our manners, the excessive consumption of foreign superfluities, and the necessity of restricting it, as well with oeconomical as republican views, he moved that a Committee be appointed to report articles of Association for encouraging by the advice the influence and the example of the members of the Convention, oeconomy[,] frugality[,] and american manufactures. [Madison, Sept. 13, 1787, in Farrand, \"Records of the Federal Convention;\" the motion was agreed to without opposition]</blockquote><blockquote>科尔·梅森（Col Mason）——他曾不成功地提出制定奢侈规定的权力。他还没有忘记他的目标。在谈论我们的行为的奢侈、对外国奢侈品的过度消费以及限制它的必要性时，他提议任命一个委员会，以通过委员会成员的建议、影响和示范来鼓励经济、节俭和美国制造业的协会条款。[麦迪逊，1787年9月13日，引自法兰德的《联邦会议记录》； 该动议未遭反对通过]</blockquote>"
    },
    {
      "title": "<h2 id=\"#29780\" class=\"scroll-m-16 text-3xl font-bold flex items-center\">economy<div class=\"pl-2 flex-1 text-textSecondary text-xl font-serif\">(adj.)</div></h2>",
      "html": "<p>1821年作为广告术语，最初的意思只是“更便宜”，后来变成“更大，因此每单位或数量更便宜”（1950年）。参见 <a title=\"Etymology, meaning and definition of economy \" class=\"crossreference notranslate\" href=\"/cn/word/economy\">economy</a>（n.经济）。</p>"
    }
  ],
  "relate": [
    {
      "title": "dispensation<div class=\"pl-2 flex-1 text-textSecondary text-xl font-serif\">(n.)</div>",
      "html": "<p>14世纪晚期， <i class=\"foreign notranslate\">dispensacioun</i>，“支配权”，也指“分配或分发的行为”，还指“在某些特定情况下放宽法律规定”，源自古法语 <i class=\"foreign notranslate\">despensacion</i>（12世纪，现代法语 <i class=\"foreign notranslate\">dispensation</i>）和直接源自拉丁语 <i class=\"foreign notranslate\">dispensationem</i>（主格 <i class=\"foreign notranslate\">dispensatio</i>）“管理，负责”，动作名词，来自 <i class=\"foreign notranslate\">dispensare</i> “支付，管理，按重量分配”（参见 <a title=\"Etymology, meaning and definition of dispense \" class=\"crossreference notranslate\" href=\"/cn/word/dispense\">dispense</a>）。相关： <i class=\"foreign notranslate\">Dispensational</i>。</p><p>神学意义上的“上帝发展他的目的并向人类显露自己的方法或计划”（14世纪晚期）源自拉丁词汇用于翻译希腊语 <i class=\"foreign notranslate\">oikonomoia</i> “职务，管理方法”（参见 <a title=\"Etymology, meaning and definition of economy \" class=\"crossreference notranslate\" href=\"/cn/word/economy\">economy</a>）。因此，“特定时期内宗教体系盛行”（1640年代），如 <i class=\"foreign notranslate\">Patriarchal, Mosaic, Christian</i> 等。还有“神圣的恩典或惩罚的特定分配”（1650年代）。</p>"
    },
    {
      "title": "econometric<div class=\"pl-2 flex-1 text-textSecondary text-xl font-serif\">(adj.)</div>",
      "html": "<p>1933年，由 <a title=\"Etymology, meaning and definition of economy \" class=\"crossreference notranslate\" href=\"/cn/word/economy\">economy</a> 和 <a title=\"Etymology, meaning and definition of -metric \" class=\"crossreference notranslate\" href=\"/cn/word/-metric\">-metric</a> 组成。相关词汇： <i class=\"foreign notranslate\">Econometrics</i>。</p>"
    }
  ]
}