{
  "word": "envisage",
  "wordRoot": [
    {
      "title": "<span id=\"#8759\" class=\"scroll-m-16 text-3xl font-bold flex items-center\"><h1 class=\"inline !mb-1 scroll-m-16 text-3xl font-bold\">envisage</h1><div class=\"pl-2 flex-1 text-textSecondary text-xl font-serif\">(v.)</div></span>",
      "html": "<p>1778年，意为“面对”，源自法语 <i class=\"foreign notranslate\">envisager</i> “面对”，由 <i class=\"foreign notranslate\">en-</i> “在……之内”（参见 <a title=\"Etymology, meaning and definition of en- \" class=\"crossreference notranslate\" href=\"/cn/word/en-\">en-</a>（1））和 <i class=\"foreign notranslate\">visage</i> “面孔”（参见 <a title=\"Etymology, meaning and definition of visage \" class=\"crossreference notranslate\" href=\"/cn/word/visage\">visage</a>）组成。因此，“理解，思考”（1837）。相关词汇： <i class=\"foreign notranslate\">Envisaged</i>； <i class=\"foreign notranslate\">envisaging</i>； <i class=\"foreign notranslate\">envisagement</i>。</p>"
    }
  ],
  "relate": [
    {
      "title": "visage<div class=\"pl-2 flex-1 text-textSecondary text-xl font-serif\">(n.)</div>",
      "html": "<p>大约1300年，来自盎格鲁-法语和古法语 <i class=\"foreign notranslate\">visage</i> “脸，面容； 肖像”，源自 <i class=\"foreign notranslate\">vis</i> “脸，外貌”，源自拉丁语 <i class=\"foreign notranslate\">visus</i> “一看，视觉”，源自 <i class=\"foreign notranslate\">videre</i> “看见”的过去分词词干（来自 PIE 词根 <a rel=\"nofollow\" title=\"Etymology, meaning and definition of *weid- \" class=\"crossreference notranslate\" href=\"/cn/word/*weid-\">*weid-</a> “看见”）。1958年，来自法语的 <i class=\"foreign notranslate\">Visagiste</i> “化妆师”。</p>"
    },
    {
      "title": "en-<div class=\"pl-2 flex-1 text-textSecondary text-xl font-serif\">(1)</div>",
      "html": "<p>这个词缀的意思是“在； 进入”，源自法语和古法语 <i class=\"foreign notranslate\">en-</i>，源自拉丁语 <i class=\"foreign notranslate\">in-</i>（来自 PIE 词根 <a rel=\"nofollow\" title=\"Etymology, meaning and definition of *en \" class=\"crossreference notranslate\" href=\"/cn/word/*en\">*en</a> “在”）。通常在 <i class=\"foreign notranslate\">-p-</i> 、<i class=\"foreign notranslate\">-b-</i> 、<i class=\"foreign notranslate\">-m-</i> 、<i class=\"foreign notranslate\">-l-</i> 和 <i class=\"foreign notranslate\">-r-</i> 之前同化。拉丁语 <i class=\"foreign notranslate\">in-</i> 在法语、西班牙语、葡萄牙语中变成了 <i class=\"foreign notranslate\">en-</i>，但在意大利语中仍然是 <i class=\"foreign notranslate\">in-</i>。</p><p>此外，它还与本土和进口元素一起使用，从名词和形容词中形成动词，意思是“放在或上”（<i class=\"foreign notranslate\">encircle</i>），也可以表示“使成为，使变成”（<i class=\"foreign notranslate\">endear</i>），并用作强调语气（<i class=\"foreign notranslate\">enclose</i>）。法语中的拼写变体被带入中古英语中，解释了 <a title=\"Etymology, meaning and definition of ensure \" class=\"crossreference notranslate\" href=\"/cn/word/ensure\">ensure</a>/<a title=\"Etymology, meaning and definition of insure \" class=\"crossreference notranslate\" href=\"/cn/word/insure\">insure</a> 等类似之处，英语中的大多数 <i class=\"foreign notranslate\">en-</i> 单词曾经或另有变体 <i class=\"foreign notranslate\">in-</i>，反之亦然。</p>"
    }
  ]
}