{
  "word": "fifth",
  "wordRoot": [
    {
      "title": "<span id=\"#5923\" class=\"scroll-m-16 text-3xl font-bold flex items-center\"><h1 class=\"inline !mb-1 scroll-m-16 text-3xl font-bold\">fifth</h1><div class=\"pl-2 flex-1 text-textSecondary text-xl font-serif\">(adj., n.)</div></span>",
      "html": "<p>\"第四个之后的下一个； 序数词； 被视为整体被分为五等份之一的其中之一； \"公元1200年，源自古英语 <span class=\"foreign notranslate\">fifta</span> \"第五\"，源自原始日耳曼语 <span class=\"foreign notranslate\">*finftan-</span>（也源自古弗里斯兰语 <span class=\"foreign notranslate\">fifta</span> 、古撒克逊语 <span class=\"foreign notranslate\">fifto</span> 、古诺尔斯语 <span class=\"foreign notranslate\">fimmti</span> 、荷兰语 <span class=\"foreign notranslate\">vijfde</span> 、古高地德语 <span class=\"foreign notranslate\">fimfto</span> 、德语 <span class=\"foreign notranslate\">fünfte</span> 、哥特语 <span class=\"foreign notranslate\">fimfta), </span>，源自原始日耳曼语 <span class=\"foreign notranslate\">fimfe</span> \"五\"（源自 PIE 词根 <a href=\"/cn/word/*penkwe-\" title=\"Etymology, meaning and definition of *penkwe- \" rel=\"nofollow\" class=\"crossreference notranslate\">*penkwe-</a> \"五\"）+ * <span class=\"foreign notranslate\">-tha</span>，用于构成序数词的词素（参见 <a href=\"/cn/word/-th\" title=\"Etymology, meaning and definition of -th \" class=\"crossreference notranslate\">-th</a>（1））。正常发展应该是 <span class=\"foreign notranslate\">fift</span>； 在14世纪受到 <a href=\"/cn/word/fourth\" title=\"Etymology, meaning and definition of fourth \" class=\"crossreference notranslate\">fourth</a> 的影响而改变。</p><ins class=\"adsbygoogle relative inline-block transition-all inline-block h-[250px] w-[300px]\" data-ad-slot=\"4000736339\" data-adtest=\"off\" data-ad-format=\"auto\" data-full-width-responsive=\"true\"></ins><p>名词意为\"一加仑酒的五分之一\"，首次记录于1938年，美国英语； 在音乐意义上的名词可追溯至16世纪90年代。<i class=\"foreign notranslate\"><strong>Fifth Avenue</strong></i>（在纽约市）自至少1858年以来被用于比喻\"优雅，品味\"。<i class=\"foreign notranslate\"><strong>Fifth wheel</strong></i> \"多余的人或物\"可追溯至1630年代。它还是一个有用的装置的名称，指的是放置在前轴上以支撑和便于转弯的\"车轮板或圆形铁片\"（1825年）。有时这个短语也被颠倒过来，给予一个积极的意义，即\"一个谨慎的驾驶员应该随身携带的东西，以防其他人出故障\"（1817年）。<i class=\"foreign notranslate\"><strong>Fifth-monarchy-man</strong></i>，17世纪用于指\"无政府主义狂热者\"，是对但以理书2:44的引用。</p>"
    }
  ],
  "relate": [
    {
      "title": "fourth<div class=\"pl-2 flex-1 text-textSecondary text-xl font-serif\">(adj., n.)</div>",
      "html": "<p>\"第三之后的下一个； 序数词； 被视为整体分为四等份之一的； \"15世纪中受 <i class=\"foreign notranslate\">four</i> 影响而改变的，源自 <i class=\"foreign notranslate\">ferthe</i>，来自古英语 <i class=\"foreign notranslate\">feorða</i> 的\"第四\"，源自原始日耳曼语 <i class=\"foreign notranslate\">*feurthan</i>（还有古撒克逊语 <i class=\"foreign notranslate\">fiortho</i>，古诺尔斯语 <i class=\"foreign notranslate\">fiorðe</i>，荷兰语 <i class=\"foreign notranslate\">vierde</i>，古高地德语 <i class=\"foreign notranslate\">fiordo</i>，德语 <i class=\"foreign notranslate\">vierte</i>）； 参见 <a title=\"Etymology, meaning and definition of four \" class=\"crossreference notranslate\" href=\"/cn/word/four\">four</a> 和 <a title=\"Etymology, meaning and definition of -th \" class=\"crossreference notranslate\" href=\"/cn/word/-th\">-th</a>（1）。作为名词，从1590年代开始，既用于分数，也用于音乐。</p><p>在拒绝异教徒的平日名称的老克瓦克人中， <i class=\"foreign notranslate\">fourth day</i> 是星期三，通常是礼拜会的次要日子。<i class=\"foreign notranslate\"><strong>Fourth-dimension</strong></i> 可追溯到1844年。戏剧上的 <i class=\"foreign notranslate\"><strong>fourth wall</strong></i> 源自1807年。将 <i class=\"foreign notranslate\"><strong>Fourth of July</strong></i> 作为美国独立纪元的庆祝活动可追溯到1777年。</p><blockquote class=\"bq-origin\">That there is due to Daniel Smith, of the city tavern, for his bill of expences of Congress, on the 4 of July last, including a balance of an old account, the sum of 729 68/90 dollars; also a bill for materials, workmanship, &amp;c furnished for the fire works on the 4 July, the sum of 102 69/90 dollars .... [Auditor General's report, Aug. 8, 1777, Journals of Congress, vol. VII]</blockquote><blockquote>根据大陆会议的记载，1777年8月8日的审计长报告，对于丹尼尔·史密斯在去年7月4日的国会开支，包括旧账户的余额，应支付729 68/90美元； 此外，还有一张关于7月4日烟火材料、工艺等费用的账单，金额为102 69/90美元.... [大陆会议记录，第七卷]</blockquote>"
    },
    {
      "title": "*penkwe-<div class=\"pl-2 flex-1 text-textSecondary text-xl font-serif\"></div>",
      "html": "<p>“五”的原始印欧语根。</p><p>它构成了以下词语的全部或部分： <a title=\"Etymology, meaning and definition of cinquain \" class=\"crossreference notranslate\" href=\"/cn/word/cinquain\">cinquain</a>； <a title=\"Etymology, meaning and definition of cinque \" class=\"crossreference notranslate\" href=\"/cn/word/cinque\">cinque</a>； <a title=\"Etymology, meaning and definition of cinquecento \" class=\"crossreference notranslate\" href=\"/cn/word/cinquecento\">cinquecento</a>； <a title=\"Etymology, meaning and definition of cinquefoil \" class=\"crossreference notranslate\" href=\"/cn/word/cinquefoil\">cinquefoil</a>； <a title=\"Etymology, meaning and definition of fifteen \" class=\"crossreference notranslate\" href=\"/cn/word/fifteen\">fifteen</a>； <a title=\"Etymology, meaning and definition of fifth \" class=\"crossreference notranslate\" href=\"/cn/word/fifth\">fifth</a>； <a title=\"Etymology, meaning and definition of fifty \" class=\"crossreference notranslate\" href=\"/cn/word/fifty\">fifty</a>； <a title=\"Etymology, meaning and definition of fin \" class=\"crossreference notranslate\" href=\"/cn/word/fin\">fin</a>（n.）“五美元钞票”； <a title=\"Etymology, meaning and definition of finger \" class=\"crossreference notranslate\" href=\"/cn/word/finger\">finger</a>； <a title=\"Etymology, meaning and definition of fist \" class=\"crossreference notranslate\" href=\"/cn/word/fist\">fist</a>； <a title=\"Etymology, meaning and definition of five \" class=\"crossreference notranslate\" href=\"/cn/word/five\">five</a>； <a title=\"Etymology, meaning and definition of foist \" class=\"crossreference notranslate\" href=\"/cn/word/foist\">foist</a>； <a title=\"Etymology, meaning and definition of keno \" class=\"crossreference notranslate\" href=\"/cn/word/keno\">keno</a>； <a title=\"Etymology, meaning and definition of parcheesi \" class=\"crossreference notranslate\" href=\"/cn/word/parcheesi\">parcheesi</a>； <a title=\"Etymology, meaning and definition of penta- \" class=\"crossreference notranslate\" href=\"/cn/word/penta-\">penta-</a>； <a title=\"Etymology, meaning and definition of pentacle \" class=\"crossreference notranslate\" href=\"/cn/word/pentacle\">pentacle</a>； <a title=\"Etymology, meaning and definition of pentad \" class=\"crossreference notranslate\" href=\"/cn/word/pentad\">pentad</a>； <a title=\"Etymology, meaning and definition of Pentateuch \" class=\"crossreference notranslate\" href=\"/cn/word/Pentateuch\">Pentateuch</a>； <a title=\"Etymology, meaning and definition of Pentecost \" class=\"crossreference notranslate\" href=\"/cn/word/Pentecost\">Pentecost</a>； <a title=\"Etymology, meaning and definition of pentagon \" class=\"crossreference notranslate\" href=\"/cn/word/pentagon\">pentagon</a>； <a title=\"Etymology, meaning and definition of pentagram \" class=\"crossreference notranslate\" href=\"/cn/word/pentagram\">pentagram</a>； <a title=\"Etymology, meaning and definition of pentameter \" class=\"crossreference notranslate\" href=\"/cn/word/pentameter\">pentameter</a>； <a title=\"Etymology, meaning and definition of pentathlon \" class=\"crossreference notranslate\" href=\"/cn/word/pentathlon\">pentathlon</a>； <a title=\"Etymology, meaning and definition of Pentothal \" class=\"crossreference notranslate\" href=\"/cn/word/Pentothal\">Pentothal</a>； <a title=\"Etymology, meaning and definition of Pompeii \" class=\"crossreference notranslate\" href=\"/cn/word/Pompeii\">Pompeii</a>； <a title=\"Etymology, meaning and definition of Punjab \" class=\"crossreference notranslate\" href=\"/cn/word/Punjab\">Punjab</a>； <a title=\"Etymology, meaning and definition of punch \" class=\"crossreference notranslate\" href=\"/cn/word/punch\">punch</a>（n.2）“一种混合饮料”； <a title=\"Etymology, meaning and definition of quinary \" class=\"crossreference notranslate\" href=\"/cn/word/quinary\">quinary</a>； <a title=\"Etymology, meaning and definition of quincunx \" class=\"crossreference notranslate\" href=\"/cn/word/quincunx\">quincunx</a>； <a title=\"Etymology, meaning and definition of quinella \" class=\"crossreference notranslate\" href=\"/cn/word/quinella\">quinella</a>； <a title=\"Etymology, meaning and definition of quinque- \" class=\"crossreference notranslate\" href=\"/cn/word/quinque-\">quinque-</a>； <a title=\"Etymology, meaning and definition of quinquennial \" class=\"crossreference notranslate\" href=\"/cn/word/quinquennial\">quinquennial</a>； <a title=\"Etymology, meaning and definition of quint \" class=\"crossreference notranslate\" href=\"/cn/word/quint\">quint</a>； <a title=\"Etymology, meaning and definition of quintain \" class=\"crossreference notranslate\" href=\"/cn/word/quintain\">quintain</a>； <a title=\"Etymology, meaning and definition of quintet \" class=\"crossreference notranslate\" href=\"/cn/word/quintet\">quintet</a>； <a title=\"Etymology, meaning and definition of quintile \" class=\"crossreference notranslate\" href=\"/cn/word/quintile\">quintile</a>； <a title=\"Etymology, meaning and definition of quintessence \" class=\"crossreference notranslate\" href=\"/cn/word/quintessence\">quintessence</a>； <a title=\"Etymology, meaning and definition of quintillion \" class=\"crossreference notranslate\" href=\"/cn/word/quintillion\">quintillion</a>； <a title=\"Etymology, meaning and definition of quintuple \" class=\"crossreference notranslate\" href=\"/cn/word/quintuple\">quintuple</a>。</p><p>它是假设的源头，其存在的证据由以下语言提供：梵语 <i class=\"foreign notranslate\">panca</i>，希腊语 <i class=\"foreign notranslate\">pente</i>，拉丁语 <i class=\"foreign notranslate\">quinque</i>，古教会斯拉夫语 <i class=\"foreign notranslate\">pęti</i>，立陶宛语 <i class=\"foreign notranslate\">penki</i>，古威尔士语 <i class=\"foreign notranslate\">pimp</i>，古英语 <i class=\"foreign notranslate\">fif</i>，荷兰语 <i class=\"foreign notranslate\">vijf</i>，古高地德语 <i class=\"foreign notranslate\">funf</i>。</p>"
    },
    {
      "title": "-th<div class=\"pl-2 flex-1 text-textSecondary text-xl font-serif\">(1)</div>",
      "html": "<p>“ -fold（ <i class=\"foreign notranslate\">fourth</i>， <i class=\"foreign notranslate\">tenth</i>，等）表序数的词根，来自古英语  <i class=\"foreign notranslate\">-ða</i>，源自原始日耳曼语  <i class=\"foreign notranslate\">*-tha-</i> （同源词：哥特语  <i class=\"foreign notranslate\">-da</i>， <i class=\"foreign notranslate\">-ta</i>，古高地日耳曼语  <i class=\"foreign notranslate\">-do</i>， <i class=\"foreign notranslate\">-to</i>，古诺尔斯语  <i class=\"foreign notranslate\">-di</i>， <i class=\"foreign notranslate\">-ti</i> ），源自原始印欧语言  <i class=\"foreign notranslate\">*-to-</i>，也是  <i class=\"foreign notranslate\">*-eto-</i>， <i class=\"foreign notranslate\">*-oto-</i>，接尾辞形成形容词“标志着根本概念的实现”[Watkins]。 </p><p>梵语  <i class=\"foreign notranslate\">thah</i>，希腊语  <i class=\"foreign notranslate\">-tos</i>，拉丁语  <i class=\"foreign notranslate\">-tus</i> 与其同源； 梵语  <i class=\"foreign notranslate\">ta-</i>，立陶宛语和旧教会斯拉夫语  <i class=\"foreign notranslate\">to</i>，希腊语  <i class=\"foreign notranslate\">to</i>  “那个”，拉丁语  <i class=\"foreign notranslate\">talis</i>  “诸如此类的”； 希腊语  <i class=\"foreign notranslate\">t</i><i class=\"foreign notranslate\">ē</i><i class=\"foreign notranslate\">likos</i>  “如此古老，如此年幼”，旧教会斯拉夫语  <i class=\"foreign notranslate\">toli</i>  “如此，到如此的程度”， <i class=\"foreign notranslate\">toliku</i>  “这么多”，俄语  <i class=\"foreign notranslate\">toliko</i>  “仅仅”。另见  <a title=\"Etymology, meaning and definition of -ed \" class=\"crossreference notranslate\" href=\"/cn/word/-ed\">-ed</a> 。</p>"
    }
  ]
}