{
  "word": "grand",
  "wordRoot": [
    {
      "title": "<span id=\"#11897\" class=\"scroll-m-16 text-3xl font-bold flex items-center\"><h1 class=\"inline !mb-1 scroll-m-16 text-3xl font-bold\">grand</h1><div class=\"pl-2 flex-1 text-textSecondary text-xl font-serif\">(adj.)</div></span>",
      "html": "<p>14世纪晚期， <span class=\"foreign notranslate\">grant</span> “大，巨大”（12世纪早期用于姓氏），源自盎格鲁-法语 <span class=\"foreign notranslate\">graunt</span>，直接源自古法语 <span class=\"foreign notranslate\">grant</span>， <span class=\"foreign notranslate\">grand</span>（10世纪，现代法语 <span class=\"foreign notranslate\">grand</span>）“高大的； 成年的； 伟大的，强大的，重要的； 严格的，严厉的； 广泛的； 众多的”，源自拉丁语 <span class=\"foreign notranslate\">grandis</span> “大的，伟大的； 充足的，丰富的”，也指“成年的”； 比喻地指“强大的，有力的，重要的，严厉的”，起源不明。</p><ins class=\"adsbygoogle relative inline-block transition-all inline-block h-[250px] w-[300px]\" data-ad-slot=\"4000736339\" data-adtest=\"off\" data-ad-format=\"auto\" data-full-width-responsive=\"true\"></ins><p>在通俗拉丁语中，它取代了 <i class=\"foreign notranslate\">magnus</i>，并在罗曼语言中继续存在。在拉丁语中，“高贵的，崇高的，高尚的，庄严的”等内涵。在英语中，它发展出了“令人印象深刻的”特殊意义。意思是“主要的，首要的，最重要的”（尤其是在头衔中）始于1560年代； “非常高质量或高贵的”意思始于1712年。作为一般的赞美词，“宏伟的，辉煌的”始于1816年。相关： <i class=\"foreign notranslate\">Grander</i>； <i class=\"foreign notranslate\">grandest</i>。</p><p><i class=\"foreign notranslate\"><strong>Grand jury</strong></i> 始于15世纪晚期。1797年的 <i class=\"foreign notranslate\"><strong>Grand piano</strong></i>。作为绅士教育的一部分，对欧洲主要景点的 <i class=\"foreign notranslate\"><strong>grand tour</strong></i> 自1660年代以来以那个名字被证实。美国西部科罗拉多河的 <i class=\"foreign notranslate\"><strong>Grand Canyon</strong></i> 在1869年被称为如此，由科学探险家约翰·韦斯利·鲍威尔少校推广； 早期它被称为 <i class=\"foreign notranslate\">Big Canyon</i>。关于 <i class=\"foreign notranslate\">grand slam</i>，请参见 <a title=\"Etymology, meaning and definition of slam \" class=\"crossreference notranslate\" href=\"/cn/word/slam\">slam</a>（n.2）。</p>"
    },
    {
      "title": "<h2 id=\"#41189\" class=\"scroll-m-16 text-3xl font-bold flex items-center\">grand<div class=\"pl-2 flex-1 text-textSecondary text-xl font-serif\">(n.)</div></h2>",
      "html": "<p>“千美元”，1915年，美国英语黑社会俚语，源自于 <a title=\"Etymology, meaning and definition of grand \" class=\"crossreference notranslate\" href=\"/cn/word/grand\">grand</a>（形容词）。</p>"
    }
  ],
  "relate": [
    {
      "title": "slam<div class=\"pl-2 flex-1 text-textSecondary text-xl font-serif\">(n.2)</div>",
      "html": "<p>\"赢得纸牌游戏中所有的技巧， 特别是在无零叫牌中的胜利，\" 17世纪50年代，此前它也是名为 <i class=\"foreign notranslate\">ruff</i> 的一种纸牌游戏（1620S），起源不明。</p><p>1892年记录了桥牌中的 <i class=\"foreign notranslate\">grand slam</i>; 在相关纸牌游戏中早在1800年就已被使用。 \"完全成功\" 的比喻含义出现于1920年。棒球中的含义是指\"所有基地都有人且得分的全垒打\"，由1935年开始使用，可能是从纸牌游戏的意义自然延伸出来的，并带有 <a title=\"Etymology, meaning and definition of slam \" class=\"crossreference notranslate\" href=\"/cn/word/slam\">slam</a>（n.1）的暗示。它也是20世纪20年代和30年代高尔夫球杆的一种品牌名称。</p>"
    },
    {
      "title": "aggrandize<div class=\"pl-2 flex-1 text-textSecondary text-xl font-serif\">(v.)</div>",
      "html": "<p>1630年代，“使更大，增加”，源自法语 <i class=\"foreign notranslate\">agrandiss-</i>，是 <i class=\"foreign notranslate\">agrandir</i> “增加，扩大”的现在分词词干（16世纪），最终源自拉丁语 <i class=\"foreign notranslate\">ad</i> “到”（见 <a title=\"Etymology, meaning and definition of ad- \" class=\"crossreference notranslate\" href=\"/cn/word/ad-\">ad-</a>）+ <i class=\"foreign notranslate\">grandire</i> “使伟大”，来自 <a title=\"Etymology, meaning and definition of grand \" class=\"crossreference notranslate\" href=\"/cn/word/grand\">grand</a>（形容词）的 <i class=\"foreign notranslate\">grandis</i> “大，伟大； 充足，丰富”（参见 <a title=\"Etymology, meaning and definition of grand \" class=\"crossreference notranslate\" href=\"/cn/word/grand\">grand</a>（形容词））。英语中的双重 <i class=\"foreign notranslate\">-g-</i> 拼写（法语中也曾如此）是与拉丁语中的 <i class=\"foreign notranslate\">ad-</i> 词汇类比而来。相关词汇： <i class=\"foreign notranslate\">Aggrandized</i>； <i class=\"foreign notranslate\">aggrandizing</i>。</p>"
    }
  ]
}