{
  "word": "handle",
  "wordRoot": [
    {
      "title": "<span id=\"#1432\" class=\"scroll-m-16 text-3xl font-bold flex items-center\"><h1 class=\"inline !mb-1 scroll-m-16 text-3xl font-bold\">handle</h1><div class=\"pl-2 flex-1 text-textSecondary text-xl font-serif\">(n.)</div></span>",
      "html": "<p>古英语中的 <span class=\"foreign notranslate\">handle</span> “一个手柄”（复数 <span class=\"foreign notranslate\">handla</span>），由 <a href=\"/cn/word/hand\" title=\"Etymology, meaning and definition of hand \" class=\"crossreference notranslate\">hand</a>（名词）加上表示工具的工具后缀 <a href=\"/cn/word/-el\" title=\"Etymology, meaning and definition of -el \" class=\"crossreference notranslate\">-el</a>（1）形成，表示与 <span class=\"foreign notranslate\">thumb</span> 相似的方式形成 <a href=\"/cn/word/thimble\" title=\"Etymology, meaning and definition of thimble \" class=\"crossreference notranslate\">thimble</a>， <span class=\"foreign notranslate\">spin</span> 形成 <a href=\"/cn/word/spindle\" title=\"Etymology, meaning and definition of spindle \" class=\"crossreference notranslate\">spindle</a>， <span class=\"foreign notranslate\">spin</span> 形成 <a href=\"/cn/word/spindle\" title=\"Etymology, meaning and definition of spindle \" class=\"crossreference notranslate\">spindle</a>， <span class=\"foreign notranslate\">lade</span> 形成 <a href=\"/cn/word/ladle\" title=\"Etymology, meaning and definition of ladle \" class=\"crossreference notranslate\">ladle</a>，等等。 \"昵称\"的俚语意义首次记录于1870年，最初来自于早期关于添加 <span class=\"foreign notranslate\">a handle to (one's) name</span>（1833）的表达方式，即称号，例如 <span class=\"foreign notranslate\">Mister</span> 或 <span class=\"foreign notranslate\">Sir</span>。 \"To <span class=\"foreign notranslate\">fly off the handle</span>\"（1833）是对斧头的比喻（\"To <span class=\"foreign notranslate\">be off the handle</span>\"的意思是“被激动”记录于1825年，美国英语）。 \"To <span class=\"foreign notranslate\">get a handle on</span>\"（获得控制）的记录始于1919年。</p><ins class=\"adsbygoogle relative inline-block transition-all inline-block h-[250px] w-[300px]\" data-ad-slot=\"4000736339\" data-adtest=\"off\" data-ad-format=\"auto\" data-full-width-responsive=\"true\"></ins>"
    },
    {
      "title": "<h2 id=\"#41577\" class=\"scroll-m-16 text-3xl font-bold flex items-center\">handle<div class=\"pl-2 flex-1 text-textSecondary text-xl font-serif\">(v.)</div></h2>",
      "html": "<p>中古英语 <i class=\"foreign notranslate\">hondlen</i>， <i class=\"foreign notranslate\">handlen</i>，意为“用手触摸，手持，抚摸，爱抚”，也指“处理，对待，粗暴对待”，源自古英语 <i class=\"foreign notranslate\">handlian</i>，意为“用手触摸或移动”，也指“处理，讨论”，由 <a title=\"Etymology, meaning and definition of hand \" class=\"crossreference notranslate\" href=\"/cn/word/hand\">hand</a>（名词）构成，可能带有一种频繁的后缀，如 <a title=\"Etymology, meaning and definition of fondle \" class=\"crossreference notranslate\" href=\"/cn/word/fondle\">fondle</a> 源自 <i class=\"foreign notranslate\">fond</i>。同源词包括古诺尔斯语 <i class=\"foreign notranslate\">höndla</i>，意为“抓住，捕获”，丹麦语 <i class=\"foreign notranslate\">handle</i>，意为“交易，处理”，古高地德语 <i class=\"foreign notranslate\">hantalon</i>，意为“感觉，触摸； 管理”，德语 <i class=\"foreign notranslate\">handeln</i>，意为“讨价还价，交易”。相关词汇包括 <i class=\"foreign notranslate\">Handled</i>， <a title=\"Etymology, meaning and definition of handling \" class=\"crossreference notranslate\" href=\"/cn/word/handling\">handling</a>。意为“对待”（某人，以某种方式，通常是敌意或粗暴）的含义始于公元1200年左右。商业意义上的“交易或经营”在英语中比其他日耳曼语系语言要弱，但在美国英语中得到了加强（自1888年起），因为这个词意味着某物经过某人的手，参见 <a title=\"Etymology, meaning and definition of handler \" class=\"crossreference notranslate\" href=\"/cn/word/handler\">handler</a>。</p>"
    }
  ],
  "relate": [
    {
      "title": "fondle<div class=\"pl-2 flex-1 text-textSecondary text-xl font-serif\">(v.)</div>",
      "html": "<p>1690年代，“宠爱和关爱”（现已过时），来自形容词 <a title=\"Etymology, meaning and definition of fond \" class=\"crossreference notranslate\" href=\"/cn/word/fond\">fond</a> 和频繁的后缀。或者可能来自过时的动词 <i class=\"foreign notranslate\">fond</i> “喜欢，爱，迷恋”（1520年代），来自形容词或改编自早期的 <i class=\"foreign notranslate\">fon</i>。 “爱抚”的意义首次记录于1796年。作为名词始于1833年。相关： <i class=\"foreign notranslate\">Fondled</i>； <i class=\"foreign notranslate\">fondling</i>（1670年代作为过去分词形容词）； <i class=\"foreign notranslate\">fondlesome</i>。</p>"
    },
    {
      "title": "hand<div class=\"pl-2 flex-1 text-textSecondary text-xl font-serif\">(n.)</div>",
      "html": "<p>古英语 <i class=\"foreign notranslate\">hond</i>， <i class=\"foreign notranslate\">hand</i> 指的是“人的手”，也指“一侧，部分，方向”（用于定义位置，指向右侧或左侧）； 还指“力量，控制，拥有”（基于手的握持或掌握的概念），源自原始日耳曼语 <i class=\"foreign notranslate\">*handuz</i>（也是古撒克逊语，古弗里斯兰语，荷兰语，德语 <i class=\"foreign notranslate\">hand</i>，古诺尔斯语 <i class=\"foreign notranslate\">hönd</i>，哥特语 <i class=\"foreign notranslate\">handus</i> 的来源），其起源不确定。</p><p>原始的古英语复数形式 <i class=\"foreign notranslate\">handa</i> 在中古英语中被 <i class=\"foreign notranslate\">handen</i> 取代，后来又变成了 <i class=\"foreign notranslate\">hands</i>。印欧语系中的“手”一词往往来自意味着“抓取，拿取，收集”的词根，或者是从最初只指手的一部分的词语扩展而来（例如爱尔兰语 <i class=\"foreign notranslate\">lam</i>，威尔士语 <i class=\"foreign notranslate\">llaw</i>，与拉丁语 <i class=\"foreign notranslate\">palma</i> 同源，最初的意思是“手掌”）。一个古老的词根（<a rel=\"nofollow\" title=\"Etymology, meaning and definition of *man- \" class=\"crossreference notranslate\" href=\"/cn/word/*man-\">*man-</a>（2）），由拉丁语 <i class=\"foreign notranslate\">manus</i> 代表，是古英语 <i class=\"foreign notranslate\">mund</i> “手”的来源，但更常指“保护，监护； 保护者，监护人”。</p><p>指“用手做事的工人，手艺人”是从1580年代开始的，因此也指“雇佣工人”（1630年代）和“船员中的水手”（1660年代）。指“机构，参与做某事的一部分”是从1590年代开始的。钟表和手表的意义来自1570年代。指“鼓掌一次”是从1838年开始的。4英寸（最初是3英寸）的线性度量单位始于1560年代，现在只用于表示马的高度。指“一位玩家手中的纸牌”是从1620年代开始的； 指“一轮纸牌游戏”是从1620年代开始的。指“书写”是从14世纪末开始的； 也指“某人的书写风格”（15世纪初）。指手在进行承诺方面的各种用途是在公元1200年左右出现的； 具体指“婚姻承诺”是在14世纪末出现的。</p><p><i class=\"foreign notranslate\"><strong>First hand</strong></i><strong>，</strong><i class=\"foreign notranslate\"><strong>second hand</strong></i> 等（15世纪中叶）是指某物从手传递到手的概念。<i class=\"foreign notranslate\"><strong>At hand</strong></i> 指“时间接近”是从公元1200年左右开始的，指“在范围之内”是从公元1300年左右开始的。<i class=\"foreign notranslate\"><strong>Out of hand</strong></i>（1590年代）是 <i class=\"foreign notranslate\"><strong>in hand</strong></i> “在控制之下”的反义词（公元1200年左右）。副词短语 <i class=\"foreign notranslate\"><strong>hand-over-fist</strong></i>（1803年）是航海术语，暗示通过交替地一只手接一只手地拉或攀爬。</p><p>短语 <i class=\"foreign notranslate\"><strong>on the one hand ... on the other hand</strong></i> 是从1630年代开始记录的，是对 <i class=\"foreign notranslate\">hand</i> 在身体一侧或另一侧位置的物理意义的比喻用法（如 <i class=\"foreign notranslate\">the lefthand side</i> 中），其起源可以追溯到古英语 <i class=\"foreign notranslate\">Hands up!</i>，作为警察、强盗等的命令，意味着举起双手作为屈服或不抵抗的象征。<i class=\"foreign notranslate\"><strong>Hand-to-hand</strong></i> 指“亲密接触”，用于战斗，始于公元1400年左右。<i class=\"foreign notranslate\"><strong>Hand-to-mouth</strong></i> 指“说一个人把钱花得和挣得一样快，只够维持日常生活”[巴特莱特]，始于公元1500年左右。<i class=\"foreign notranslate\"><strong>Hand-in-hand</strong></i> 指“双手紧握”，比喻意义上指“同时进行”，始于1570年代。</p>"
    }
  ]
}