{
  "word": "identify",
  "wordRoot": [
    {
      "title": "<span id=\"#1483\" class=\"scroll-m-16 text-3xl font-bold flex items-center\"><h1 class=\"inline !mb-1 scroll-m-16 text-3xl font-bold\">identify</h1><div class=\"pl-2 flex-1 text-textSecondary text-xl font-serif\">(v.)</div></span>",
      "html": "<p>1640年代，“把…看作相同的”，来自法语“<span class=\"foreign notranslate\">identifier</span>”，源自“<span class=\"foreign notranslate\">identité</span>”（见 <a href=\"/cn/word/identity\" title=\"Etymology, meaning and definition of identity \" class=\"crossreference notranslate\">identity</a>）。 “确认身份，认同为同一事物”之意首次记录于1769年。1780年有“使一个（与其他事物）融为一体，将自己与…联系在一起，认为自己是本质”之意。“作为身份标识的手段”一词的意义可追溯至1886年。相关词汇： <span class=\"foreign notranslate\">Identified</span>； <span class=\"foreign notranslate\">identifying</span>。</p><ins class=\"adsbygoogle relative inline-block transition-all inline-block h-[250px] w-[300px]\" data-ad-slot=\"4000736339\" data-adtest=\"off\" data-ad-format=\"auto\" data-full-width-responsive=\"true\"></ins>"
    }
  ],
  "relate": [
    {
      "title": "identity<div class=\"pl-2 flex-1 text-textSecondary text-xl font-serif\">(n.)</div>",
      "html": "<p>大约1600年，\"sameness, oneness, state of being the same\"一词的意思是“相同，一致，同一状态”，来源于14世纪的法语 <i class=\"foreign notranslate\">identité</i>，源自中古拉丁语的 <i class=\"foreign notranslate\">identitatem</i>（主格为 <i class=\"foreign notranslate\">identitas</i>）“sameness”，最终源自拉丁语的 <i class=\"foreign notranslate\">idem</i>（中性）“the same”（参见 <a title=\"Etymology, meaning and definition of idem \" class=\"crossreference notranslate\" href=\"/cn/word/idem\">idem</a>）。[关于拉丁语词源的讨论，请参阅 OED 中的词条。] 这个词在英语中的早期形式是 <i class=\"foreign notranslate\">idemptitie</i>（1560年代），来自中世纪拉丁语的 <i class=\"foreign notranslate\">idemptitas</i>。术语 <i class=\"foreign notranslate\"><strong>identity crisis</strong></i> 的首次记录是在1954年。<i class=\"foreign notranslate\"><strong>Identity theft</strong></i> 是在1995年被证明的。<i class=\"foreign notranslate\"><strong>Identity politics</strong></i> 最早可以追溯到1987年。</p><blockquote class=\"bq-origin\">\"[I]dentity politics\" [is] a phrase with notably wide currency in gay and lesbian communities. In common usage, the term identity politics refers to the tendency to base one's politics on a sense of personal identity—as gay, as Jewish, as Black, as female ..... [Diana Fuss, \"Essentially Speaking,\" 1989]</blockquote><blockquote>\"[I]dentity politics\"是一个在同性恋社区广泛使用的短语。在通常的用法中，\"identity politics\"指的是把政治基础建立在个人身份感上，比如同性恋、犹太人、黑人和女性等身份。[戴安娜·福斯，《基本上在说话》，1989年]</blockquote>"
    },
    {
      "title": "identifiable<div class=\"pl-2 flex-1 text-textSecondary text-xl font-serif\">(adj.)</div>",
      "html": "<p>可辨认的，1804年，来自 <a title=\"Etymology, meaning and definition of identify \" class=\"crossreference notranslate\" href=\"/cn/word/identify\">identify</a> + <a title=\"Etymology, meaning and definition of -able \" class=\"crossreference notranslate\" href=\"/cn/word/-able\">-able</a>。相关词汇： <i class=\"foreign notranslate\">Identifiably</i>。</p>"
    }
  ]
}